conversiontelemetry/conversiontelemetry.py
conversiontelemetry/curl_get.sh
conversiontelemetry/curl_post.sh
conversiontelemetry/run_app.py
conversiontelemetry/run_app_cloud.py
conversiontelemetry/setup_app.py
conversiontelemetry/stop_app_cloud.py
scripts/stop_app
conversiontelemetry-0.0.2.dist-info/METADATA
conversiontelemetry-0.0.2.dist-info/WHEEL
conversiontelemetry-0.0.2.dist-info/entry_points.txt
conversiontelemetry-0.0.2.dist-info/RECORD
