Metadata-Version: 2.1
Name: conversiontelemetry
Version: 0.0.2
Summary: A very simple application to post and get jsons to a mongodb database
Author: Anthony Galassi
Author-email: 28850131+bendhouseart@users.noreply.github.com
Requires-Python: >=3.8,<4.0
Classifier: Programming Language :: Python :: 3
Classifier: Programming Language :: Python :: 3.8
Classifier: Programming Language :: Python :: 3.9
Classifier: Programming Language :: Python :: 3.10
Classifier: Programming Language :: Python :: 3.11
Requires-Dist: fastapi (>=0.110.0,<0.111.0)
Requires-Dist: gunicorn (>=22.0.0,<23.0.0)
Requires-Dist: pymongo (>=4.6.2,<5.0.0)
Requires-Dist: python-dotenv (>=1.0.1,<2.0.0)
Requires-Dist: rich (>=13.7.1,<14.0.0)
Requires-Dist: slowapi (>=0.1.9,<0.2.0)
Requires-Dist: uvicorn (>=0.27.1,<0.28.0)
